LICENSE
MANIFEST.in
README.rst
setup.cfg
setup.py
contact_widget/__init__.py
contact_widget/admin.py
contact_widget/forms.py
contact_widget/models.py
contact_widget/urls.py
contact_widget/views.py
contact_widget.egg-info/PKG-INFO
contact_widget.egg-info/SOURCES.txt
contact_widget.egg-info/dependency_links.txt
contact_widget.egg-info/not-zip-safe
contact_widget.egg-info/requires.txt
contact_widget.egg-info/top_level.txt
contact_widget/templates/contact_widget/contact.html