Metadata-Version: 1.1
Name: contact-widget
Version: 1.0.0
Summary: A simple contact form widget for Django
Home-page: https://github.com/agusmakmun/django-contact-widget/
Author: Agus Makmun (Summon Agus)
Author-email: agus@python.web.id
License: MIT
Download-URL: https://github.com/agusmakmun/django-contact-widget/tarball/v1.0.0
Keywords: django contact widget,django contact form
Platform: UNKNOWN
Classifier: Programming Language :: Python
Classifier: Programming Language :: Python :: 2.7
Classifier: Programming Language :: Python :: 3.3
Classifier: Programming Language :: Python :: 3.4
Classifier: Programming Language :: Python :: 3.5
Classifier: License :: OSI Approved :: MIT License
Classifier: Operating System :: OS Independent
Classifier: Intended Audience :: Developers
Classifier: Framework :: Django
